{
  "xmlId" : "5719",
  "NOAAStudyId" : "4663",
  "studyName" : "Schweingruber - Stubaital Milderaun Alm - PCAB - ITRDB AUST007",
  "doi" : "https://doi.org/10.25921/e3m6-3724",
  "uuid" : "8657f6c5-8aa1-4b7d-bf05-2771e004a92f",
  "dataPublisher" : "NOAA",
  "contactInfo" : {
    "type" : "CONTACT INFORMATION",
    "shortName" : "DOC/NOAA/NESDIS/NCEI",
    "longName" : "National Centers for Environmental Information, NESDIS, NOAA, U.S. Department of Commerce ",
    "address" : "325 Broadway, E/NE31",
    "city" : "Boulder",
    "state" : "CO",
    "postalCode" : "80305-3328",
    "country" : "USA",
    "dataCenterUrl" : "https://www.ncei.noaa.gov/products/paleoclimatology",
    "email" : "paleo@noaa.gov",
    "phone" : "828-271-4800",
    "fax" : "303-497-6513",
    "constraints" : "Please cite original publication, online resource, dataset and publication DOIs (where available), and date accessed when using downloaded data. If there is no publication information, please cite investigator, title, online resource, and date accessed. The appearance of external links associated with a dataset does not constitute endorsement by the Department of Commerce/National Oceanic and Atmospheric Administration of external Web sites or the information, products or services contained therein. For other than authorized activities, the Department of Commerce/NOAA does not exercise any editorial control over the information you may find at these locations. These links are provided consistent with the stated purpose of this Department of Commerce/NOAA Web site."
  },
  "dataType" : "TREE RING",
  "investigators" : "Schweingruber, F.H.",
  "investigatorDetails" : [ {
    "firstName" : null,
    "lastName" : "Schweingruber",
    "initials" : "F.H.",
    "orcId" : null
  } ],
  "version" : "1.0",
  "funding" : [ ],
  "studyNotes" : " NOAA Template Chronology file added 2019-01-08. NOAA Template Raw Measurements file added 2019-02-05.",
  "onlineResourceLink" : "https://www.ncei.noaa.gov/access/paleo-search/study/4663",
  "difMetadataLink" : "http://www1.ncdc.noaa.gov/pub/data/metadata/published/paleo/dif/xml/noaa-tree-4663.xml",
  "isoMetadataLink" : "http://www1.ncdc.noaa.gov/pub/data/metadata/published/paleo/iso/xml/noaa-tree-4663.xml",
  "originalSource" : null,
  "dataTypeInformation" : "https://www.ncei.noaa.gov/products/paleoclimatology/tree-ring",
  "studyCode" : "AUST007",
  "scienceKeywords" : [ "Picea abies (L.) H. Karst.", "Norway spruce", "PCAB" ],
  "reconstruction" : "N",
  "contributionDate" : "2002-07-31",
  "entryId" : "noaa-tree-4663",
  "earliestYearBP" : 205,
  "mostRecentYearBP" : -25,
  "earliestYearCE" : 1745,
  "mostRecentYearCE" : 1975,
  "publication" : [ ],
  "site" : [ {
    "NOAASiteId" : "16989",
    "siteName" : "Stubaital Milderaun Alm",
    "siteCode" : null,
    "mappable" : "Y",
    "locationName" : "Continent>Europe>Western Europe>Austria",
    "geo" : {
      "geoType" : "Feature",
      "geometry" : {
        "type" : "POINT",
        "coordinates" : [ "47.13", "11.28" ]
      },
      "properties" : {
        "southernmostLatitude" : "47.13",
        "northernmostLatitude" : "47.13",
        "westernmostLongitude" : "11.28",
        "easternmostLongitude" : "11.28",
        "minElevationMeters" : "1850",
        "maxElevationMeters" : "1850"
      }
    },
    "paleoData" : [ {
      "dataTableName" : "AUST007",
      "NOAADataTableId" : "6389",
      "earliestYear" : 1745,
      "mostRecentYear" : 1975,
      "timeUnit" : "CE",
      "earliestYearBP" : 205,
      "mostRecentYearBP" : -25,
      "earliestYearCE" : 1745,
      "mostRecentYearCE" : 1975,
      "coreLengthMeters" : null,
      "dataTableNotes" : null,
      "species" : [ {
        "speciesCode" : "PCAB",
        "scientificName" : "Picea abies (L.) H. Karst.",
        "resourceId" : null,
        "commonName" : [ "Norway spruce" ]
      } ],
      "dataFile" : [ {
        "fileUrl" : "https://www.ncei.noaa.gov/pub/data/paleo/treering/measurements/correlation-stats/aust007.txt",
        "urlDescription" : "Correlation Stats",
        "linkText" : "aust007.txt",
        "variables" : [ ],
        "NOAAKeywords" : [ "earth science>paleoclimate>tree-ring>width>more info" ]
      }, {
        "fileUrl" : "https://www.ncei.noaa.gov/pub/data/paleo/treering/chronologies/europe/aust007.crn",
        "urlDescription" : "Chronology",
        "linkText" : "aust007.crn",
        "variables" : [ {
          "cvDataType" : "TREE RING",
          "cvWhat" : "age variable>age",
          "cvMaterial" : null,
          "cvError" : null,
          "cvUnit" : "time unit>age unit>year Common Era",
          "cvSeasonality" : null,
          "cvDetail" : null,
          "cvMethod" : null,
          "cvAdditionalInfo" : null,
          "cvFormat" : "Numeric",
          "cvShortName" : null
        }, {
          "cvDataType" : "TREE RING",
          "cvWhat" : "sampling metadata>number of samples",
          "cvMaterial" : null,
          "cvError" : null,
          "cvUnit" : "dimensionless>count",
          "cvSeasonality" : null,
          "cvDetail" : null,
          "cvMethod" : null,
          "cvAdditionalInfo" : null,
          "cvFormat" : "Numeric",
          "cvShortName" : null
        }, {
          "cvDataType" : "TREE RING",
          "cvWhat" : "statistical variable>proxy composite>tree ring standardized growth index",
          "cvMaterial" : null,
          "cvError" : null,
          "cvUnit" : null,
          "cvSeasonality" : null,
          "cvDetail" : "composited",
          "cvMethod" : "computational method>tree ring chronology method>standard chronology method",
          "cvAdditionalInfo" : null,
          "cvFormat" : "Numeric",
          "cvShortName" : null
        } ],
        "NOAAKeywords" : [ "earth science>paleoclimate>tree-ring>width>ring width" ]
      }, {
        "fileUrl" : "https://www.ncei.noaa.gov/pub/data/paleo/treering/chronologies/europe/aust007e.crn",
        "urlDescription" : "Chronology",
        "linkText" : "aust007e.crn",
        "variables" : [ {
          "cvDataType" : "TREE RING",
          "cvWhat" : "age variable>age",
          "cvMaterial" : null,
          "cvError" : null,
          "cvUnit" : "time unit>age unit>year Common Era",
          "cvSeasonality" : null,
          "cvDetail" : null,
          "cvMethod" : null,
          "cvAdditionalInfo" : null,
          "cvFormat" : "Numeric",
          "cvShortName" : null
        }, {
          "cvDataType" : "TREE RING",
          "cvWhat" : "sampling metadata>number of samples",
          "cvMaterial" : null,
          "cvError" : null,
          "cvUnit" : "dimensionless>count",
          "cvSeasonality" : null,
          "cvDetail" : null,
          "cvMethod" : null,
          "cvAdditionalInfo" : null,
          "cvFormat" : "Numeric",
          "cvShortName" : null
        }, {
          "cvDataType" : "TREE RING",
          "cvWhat" : "statistical variable>proxy composite>tree ring standardized growth index",
          "cvMaterial" : null,
          "cvError" : null,
          "cvUnit" : null,
          "cvSeasonality" : null,
          "cvDetail" : "composited",
          "cvMethod" : "computational method>tree ring chronology method>standard chronology method",
          "cvAdditionalInfo" : "reconstructed from earlywood width",
          "cvFormat" : "Numeric",
          "cvShortName" : null
        } ],
        "NOAAKeywords" : [ "earth science>paleoclimate>tree-ring>width>earlywood width" ]
      }, {
        "fileUrl" : "https://www.ncei.noaa.gov/pub/data/paleo/treering/chronologies/europe/aust007l.crn",
        "urlDescription" : "Chronology",
        "linkText" : "aust007l.crn",
        "variables" : [ {
          "cvDataType" : "TREE RING",
          "cvWhat" : "age variable>age",
          "cvMaterial" : null,
          "cvError" : null,
          "cvUnit" : "time unit>age unit>year Common Era",
          "cvSeasonality" : null,
          "cvDetail" : null,
          "cvMethod" : null,
          "cvAdditionalInfo" : null,
          "cvFormat" : "Numeric",
          "cvShortName" : null
        }, {
          "cvDataType" : "TREE RING",
          "cvWhat" : "sampling metadata>number of samples",
          "cvMaterial" : null,
          "cvError" : null,
          "cvUnit" : "dimensionless>count",
          "cvSeasonality" : null,
          "cvDetail" : null,
          "cvMethod" : null,
          "cvAdditionalInfo" : null,
          "cvFormat" : "Numeric",
          "cvShortName" : null
        }, {
          "cvDataType" : "TREE RING",
          "cvWhat" : "statistical variable>proxy composite>tree ring standardized growth index",
          "cvMaterial" : null,
          "cvError" : null,
          "cvUnit" : null,
          "cvSeasonality" : null,
          "cvDetail" : "composited",
          "cvMethod" : "computational method>tree ring chronology method>standard chronology method",
          "cvAdditionalInfo" : "reconstructed from latewood width",
          "cvFormat" : "Numeric",
          "cvShortName" : null
        } ],
        "NOAAKeywords" : [ "earth science>paleoclimate>tree-ring>width>latewood width" ]
      }, {
        "fileUrl" : "https://www.ncei.noaa.gov/pub/data/paleo/treering/chronologies/europe/aust007n.crn",
        "urlDescription" : "Chronology",
        "linkText" : "aust007n.crn",
        "variables" : [ {
          "cvDataType" : "TREE RING",
          "cvWhat" : "age variable>age",
          "cvMaterial" : null,
          "cvError" : null,
          "cvUnit" : "time unit>age unit>year Common Era",
          "cvSeasonality" : null,
          "cvDetail" : null,
          "cvMethod" : null,
          "cvAdditionalInfo" : null,
          "cvFormat" : "Numeric",
          "cvShortName" : null
        }, {
          "cvDataType" : "TREE RING",
          "cvWhat" : "sampling metadata>number of samples",
          "cvMaterial" : null,
          "cvError" : null,
          "cvUnit" : "dimensionless>count",
          "cvSeasonality" : null,
          "cvDetail" : null,
          "cvMethod" : null,
          "cvAdditionalInfo" : null,
          "cvFormat" : "Numeric",
          "cvShortName" : null
        }, {
          "cvDataType" : "TREE RING",
          "cvWhat" : "statistical variable>proxy composite>tree ring standardized growth index",
          "cvMaterial" : null,
          "cvError" : null,
          "cvUnit" : null,
          "cvSeasonality" : null,
          "cvDetail" : "composited",
          "cvMethod" : "computational method>tree ring chronology method>standard chronology method",
          "cvAdditionalInfo" : "reconstructed from minimum density",
          "cvFormat" : "Numeric",
          "cvShortName" : null
        } ],
        "NOAAKeywords" : [ "earth science>paleoclimate>tree-ring>density>minimum density" ]
      }, {
        "fileUrl" : "https://www.ncei.noaa.gov/pub/data/paleo/treering/chronologies/europe/aust007x.crn",
        "urlDescription" : "Chronology",
        "linkText" : "aust007x.crn",
        "variables" : [ {
          "cvDataType" : "TREE RING",
          "cvWhat" : "age variable>age",
          "cvMaterial" : null,
          "cvError" : null,
          "cvUnit" : "time unit>age unit>year Common Era",
          "cvSeasonality" : null,
          "cvDetail" : null,
          "cvMethod" : null,
          "cvAdditionalInfo" : null,
          "cvFormat" : "Numeric",
          "cvShortName" : null
        }, {
          "cvDataType" : "TREE RING",
          "cvWhat" : "sampling metadata>number of samples",
          "cvMaterial" : null,
          "cvError" : null,
          "cvUnit" : "dimensionless>count",
          "cvSeasonality" : null,
          "cvDetail" : null,
          "cvMethod" : null,
          "cvAdditionalInfo" : null,
          "cvFormat" : "Numeric",
          "cvShortName" : null
        }, {
          "cvDataType" : "TREE RING",
          "cvWhat" : "statistical variable>proxy composite>tree ring standardized growth index",
          "cvMaterial" : null,
          "cvError" : null,
          "cvUnit" : null,
          "cvSeasonality" : null,
          "cvDetail" : "composited",
          "cvMethod" : "computational method>tree ring chronology method>standard chronology method",
          "cvAdditionalInfo" : "reconstructed from maximum density",
          "cvFormat" : "Numeric",
          "cvShortName" : null
        } ],
        "NOAAKeywords" : [ "earth science>paleoclimate>tree-ring>density>maximum density" ]
      }, {
        "fileUrl" : "https://www.ncei.noaa.gov/pub/data/paleo/treering/chronologies/europe/aust007-noaa.crn",
        "urlDescription" : "Chronology - NOAA Template File",
        "linkText" : "aust007-noaa.crn",
        "variables" : [ {
          "cvDataType" : "TREE RING",
          "cvWhat" : "age variable>age",
          "cvMaterial" : null,
          "cvError" : null,
          "cvUnit" : "time unit>age unit>year Common Era",
          "cvSeasonality" : null,
          "cvDetail" : null,
          "cvMethod" : null,
          "cvAdditionalInfo" : null,
          "cvFormat" : "Numeric",
          "cvShortName" : null
        }, {
          "cvDataType" : "TREE RING",
          "cvWhat" : "sampling metadata>number of samples",
          "cvMaterial" : null,
          "cvError" : null,
          "cvUnit" : "dimensionless>count",
          "cvSeasonality" : null,
          "cvDetail" : null,
          "cvMethod" : null,
          "cvAdditionalInfo" : null,
          "cvFormat" : "Numeric",
          "cvShortName" : null
        }, {
          "cvDataType" : "TREE RING",
          "cvWhat" : "statistical variable>proxy composite>tree ring standardized growth index",
          "cvMaterial" : null,
          "cvError" : null,
          "cvUnit" : null,
          "cvSeasonality" : null,
          "cvDetail" : "composited",
          "cvMethod" : "computational method>tree ring chronology method>standard chronology method",
          "cvAdditionalInfo" : null,
          "cvFormat" : "Numeric",
          "cvShortName" : null
        } ],
        "NOAAKeywords" : [ "earth science>paleoclimate>tree-ring>width>ring width" ]
      }, {
        "fileUrl" : "https://www.ncei.noaa.gov/pub/data/paleo/treering/chronologies/europe/aust007r-noaa.crn",
        "urlDescription" : "Chronology - NOAA Template File",
        "linkText" : "aust007r-noaa.crn",
        "variables" : [ {
          "cvDataType" : "TREE RING",
          "cvWhat" : "age variable>age",
          "cvMaterial" : null,
          "cvError" : null,
          "cvUnit" : "time unit>age unit>year Common Era",
          "cvSeasonality" : null,
          "cvDetail" : null,
          "cvMethod" : null,
          "cvAdditionalInfo" : null,
          "cvFormat" : "Numeric",
          "cvShortName" : null
        }, {
          "cvDataType" : "TREE RING",
          "cvWhat" : "statistical variable>proxy composite>tree ring standardized growth index",
          "cvMaterial" : null,
          "cvError" : null,
          "cvUnit" : null,
          "cvSeasonality" : null,
          "cvDetail" : "composited",
          "cvMethod" : "computational method>tree ring chronology method>residual chronology method",
          "cvAdditionalInfo" : null,
          "cvFormat" : "Numeric",
          "cvShortName" : null
        }, {
          "cvDataType" : "TREE RING",
          "cvWhat" : "sampling metadata>number of samples",
          "cvMaterial" : null,
          "cvError" : null,
          "cvUnit" : "dimensionless>count",
          "cvSeasonality" : null,
          "cvDetail" : null,
          "cvMethod" : null,
          "cvAdditionalInfo" : null,
          "cvFormat" : "Numeric",
          "cvShortName" : null
        } ],
        "NOAAKeywords" : [ "earth science>paleoclimate>tree-ring>width>ring width" ]
      }, {
        "fileUrl" : "https://www.ncei.noaa.gov/pub/data/paleo/treering/chronologies/europe/aust007a-noaa.crn",
        "urlDescription" : "Chronology - NOAA Template File",
        "linkText" : "aust007a-noaa.crn",
        "variables" : [ {
          "cvDataType" : "TREE RING",
          "cvWhat" : "age variable>age",
          "cvMaterial" : null,
          "cvError" : null,
          "cvUnit" : "time unit>age unit>year Common Era",
          "cvSeasonality" : null,
          "cvDetail" : null,
          "cvMethod" : null,
          "cvAdditionalInfo" : null,
          "cvFormat" : "Numeric",
          "cvShortName" : null
        }, {
          "cvDataType" : "TREE RING",
          "cvWhat" : "statistical variable>proxy composite>tree ring standardized growth index",
          "cvMaterial" : null,
          "cvError" : null,
          "cvUnit" : null,
          "cvSeasonality" : null,
          "cvDetail" : "composited",
          "cvMethod" : "computational method>tree ring chronology method>ARSTAN chronology method",
          "cvAdditionalInfo" : null,
          "cvFormat" : "Numeric",
          "cvShortName" : null
        }, {
          "cvDataType" : "TREE RING",
          "cvWhat" : "sampling metadata>number of samples",
          "cvMaterial" : null,
          "cvError" : null,
          "cvUnit" : "dimensionless>count",
          "cvSeasonality" : null,
          "cvDetail" : null,
          "cvMethod" : null,
          "cvAdditionalInfo" : null,
          "cvFormat" : "Numeric",
          "cvShortName" : null
        } ],
        "NOAAKeywords" : [ "earth science>paleoclimate>tree-ring>width>ring width" ]
      }, {
        "fileUrl" : "https://www.ncei.noaa.gov/pub/data/paleo/treering/chronologies/europe/aust007e-noaa.crn",
        "urlDescription" : "Chronology - NOAA Template File",
        "linkText" : "aust007e-noaa.crn",
        "variables" : [ {
          "cvDataType" : "TREE RING",
          "cvWhat" : "age variable>age",
          "cvMaterial" : null,
          "cvError" : null,
          "cvUnit" : "time unit>age unit>year Common Era",
          "cvSeasonality" : null,
          "cvDetail" : null,
          "cvMethod" : null,
          "cvAdditionalInfo" : null,
          "cvFormat" : "Numeric",
          "cvShortName" : null
        }, {
          "cvDataType" : "TREE RING",
          "cvWhat" : "sampling metadata>number of samples",
          "cvMaterial" : null,
          "cvError" : null,
          "cvUnit" : "dimensionless>count",
          "cvSeasonality" : null,
          "cvDetail" : null,
          "cvMethod" : null,
          "cvAdditionalInfo" : null,
          "cvFormat" : "Numeric",
          "cvShortName" : null
        }, {
          "cvDataType" : "TREE RING",
          "cvWhat" : "statistical variable>proxy composite>tree ring standardized growth index",
          "cvMaterial" : null,
          "cvError" : null,
          "cvUnit" : null,
          "cvSeasonality" : null,
          "cvDetail" : "composited",
          "cvMethod" : "computational method>tree ring chronology method>standard chronology method",
          "cvAdditionalInfo" : "reconstructed from earlywood width",
          "cvFormat" : "Numeric",
          "cvShortName" : null
        } ],
        "NOAAKeywords" : [ "earth science>paleoclimate>tree-ring>width>earlywood width" ]
      }, {
        "fileUrl" : "https://www.ncei.noaa.gov/pub/data/paleo/treering/chronologies/europe/aust007er-noaa.crn",
        "urlDescription" : "Chronology - NOAA Template File",
        "linkText" : "aust007er-noaa.crn",
        "variables" : [ {
          "cvDataType" : "TREE RING",
          "cvWhat" : "age variable>age",
          "cvMaterial" : null,
          "cvError" : null,
          "cvUnit" : "time unit>age unit>year Common Era",
          "cvSeasonality" : null,
          "cvDetail" : null,
          "cvMethod" : null,
          "cvAdditionalInfo" : null,
          "cvFormat" : "Numeric",
          "cvShortName" : null
        }, {
          "cvDataType" : "TREE RING",
          "cvWhat" : "statistical variable>proxy composite>tree ring standardized growth index",
          "cvMaterial" : null,
          "cvError" : null,
          "cvUnit" : null,
          "cvSeasonality" : null,
          "cvDetail" : "composited",
          "cvMethod" : "computational method>tree ring chronology method>residual chronology method",
          "cvAdditionalInfo" : "reconstructed from earlywood width",
          "cvFormat" : "Numeric",
          "cvShortName" : null
        }, {
          "cvDataType" : "TREE RING",
          "cvWhat" : "sampling metadata>number of samples",
          "cvMaterial" : null,
          "cvError" : null,
          "cvUnit" : "dimensionless>count",
          "cvSeasonality" : null,
          "cvDetail" : null,
          "cvMethod" : null,
          "cvAdditionalInfo" : null,
          "cvFormat" : "Numeric",
          "cvShortName" : null
        } ],
        "NOAAKeywords" : [ "earth science>paleoclimate>tree-ring>width>earlywood width" ]
      }, {
        "fileUrl" : "https://www.ncei.noaa.gov/pub/data/paleo/treering/chronologies/europe/aust007ea-noaa.crn",
        "urlDescription" : "Chronology - NOAA Template File",
        "linkText" : "aust007ea-noaa.crn",
        "variables" : [ {
          "cvDataType" : "TREE RING",
          "cvWhat" : "age variable>age",
          "cvMaterial" : null,
          "cvError" : null,
          "cvUnit" : "time unit>age unit>year Common Era",
          "cvSeasonality" : null,
          "cvDetail" : null,
          "cvMethod" : null,
          "cvAdditionalInfo" : null,
          "cvFormat" : "Numeric",
          "cvShortName" : null
        }, {
          "cvDataType" : "TREE RING",
          "cvWhat" : "statistical variable>proxy composite>tree ring standardized growth index",
          "cvMaterial" : null,
          "cvError" : null,
          "cvUnit" : null,
          "cvSeasonality" : null,
          "cvDetail" : "composited",
          "cvMethod" : "computational method>tree ring chronology method>ARSTAN chronology method",
          "cvAdditionalInfo" : "reconstructed from earlywood width",
          "cvFormat" : "Numeric",
          "cvShortName" : null
        }, {
          "cvDataType" : "TREE RING",
          "cvWhat" : "sampling metadata>number of samples",
          "cvMaterial" : null,
          "cvError" : null,
          "cvUnit" : "dimensionless>count",
          "cvSeasonality" : null,
          "cvDetail" : null,
          "cvMethod" : null,
          "cvAdditionalInfo" : null,
          "cvFormat" : "Numeric",
          "cvShortName" : null
        } ],
        "NOAAKeywords" : [ "earth science>paleoclimate>tree-ring>width>earlywood width" ]
      }, {
        "fileUrl" : "https://www.ncei.noaa.gov/pub/data/paleo/treering/chronologies/europe/aust007l-noaa.crn",
        "urlDescription" : "Chronology - NOAA Template File",
        "linkText" : "aust007l-noaa.crn",
        "variables" : [ {
          "cvDataType" : "TREE RING",
          "cvWhat" : "age variable>age",
          "cvMaterial" : null,
          "cvError" : null,
          "cvUnit" : "time unit>age unit>year Common Era",
          "cvSeasonality" : null,
          "cvDetail" : null,
          "cvMethod" : null,
          "cvAdditionalInfo" : null,
          "cvFormat" : "Numeric",
          "cvShortName" : null
        }, {
          "cvDataType" : "TREE RING",
          "cvWhat" : "sampling metadata>number of samples",
          "cvMaterial" : null,
          "cvError" : null,
          "cvUnit" : "dimensionless>count",
          "cvSeasonality" : null,
          "cvDetail" : null,
          "cvMethod" : null,
          "cvAdditionalInfo" : null,
          "cvFormat" : "Numeric",
          "cvShortName" : null
        }, {
          "cvDataType" : "TREE RING",
          "cvWhat" : "statistical variable>proxy composite>tree ring standardized growth index",
          "cvMaterial" : null,
          "cvError" : null,
          "cvUnit" : null,
          "cvSeasonality" : null,
          "cvDetail" : "composited",
          "cvMethod" : "computational method>tree ring chronology method>standard chronology method",
          "cvAdditionalInfo" : "reconstructed from latewood width",
          "cvFormat" : "Numeric",
          "cvShortName" : null
        } ],
        "NOAAKeywords" : [ "earth science>paleoclimate>tree-ring>width>latewood width" ]
      }, {
        "fileUrl" : "https://www.ncei.noaa.gov/pub/data/paleo/treering/chronologies/europe/aust007lr-noaa.crn",
        "urlDescription" : "Chronology - NOAA Template File",
        "linkText" : "aust007lr-noaa.crn",
        "variables" : [ {
          "cvDataType" : "TREE RING",
          "cvWhat" : "age variable>age",
          "cvMaterial" : null,
          "cvError" : null,
          "cvUnit" : "time unit>age unit>year Common Era",
          "cvSeasonality" : null,
          "cvDetail" : null,
          "cvMethod" : null,
          "cvAdditionalInfo" : null,
          "cvFormat" : "Numeric",
          "cvShortName" : null
        }, {
          "cvDataType" : "TREE RING",
          "cvWhat" : "statistical variable>proxy composite>tree ring standardized growth index",
          "cvMaterial" : null,
          "cvError" : null,
          "cvUnit" : null,
          "cvSeasonality" : null,
          "cvDetail" : "composited",
          "cvMethod" : "computational method>tree ring chronology method>residual chronology method",
          "cvAdditionalInfo" : "reconstructed from latewood width",
          "cvFormat" : "Numeric",
          "cvShortName" : null
        }, {
          "cvDataType" : "TREE RING",
          "cvWhat" : "sampling metadata>number of samples",
          "cvMaterial" : null,
          "cvError" : null,
          "cvUnit" : "dimensionless>count",
          "cvSeasonality" : null,
          "cvDetail" : null,
          "cvMethod" : null,
          "cvAdditionalInfo" : null,
          "cvFormat" : "Numeric",
          "cvShortName" : null
        } ],
        "NOAAKeywords" : [ "earth science>paleoclimate>tree-ring>width>latewood width" ]
      }, {
        "fileUrl" : "https://www.ncei.noaa.gov/pub/data/paleo/treering/chronologies/europe/aust007la-noaa.crn",
        "urlDescription" : "Chronology - NOAA Template File",
        "linkText" : "aust007la-noaa.crn",
        "variables" : [ {
          "cvDataType" : "TREE RING",
          "cvWhat" : "age variable>age",
          "cvMaterial" : null,
          "cvError" : null,
          "cvUnit" : "time unit>age unit>year Common Era",
          "cvSeasonality" : null,
          "cvDetail" : null,
          "cvMethod" : null,
          "cvAdditionalInfo" : null,
          "cvFormat" : "Numeric",
          "cvShortName" : null
        }, {
          "cvDataType" : "TREE RING",
          "cvWhat" : "statistical variable>proxy composite>tree ring standardized growth index",
          "cvMaterial" : null,
          "cvError" : null,
          "cvUnit" : null,
          "cvSeasonality" : null,
          "cvDetail" : "composited",
          "cvMethod" : "computational method>tree ring chronology method>ARSTAN chronology method",
          "cvAdditionalInfo" : "reconstructed from latewood width",
          "cvFormat" : "Numeric",
          "cvShortName" : null
        }, {
          "cvDataType" : "TREE RING",
          "cvWhat" : "sampling metadata>number of samples",
          "cvMaterial" : null,
          "cvError" : null,
          "cvUnit" : "dimensionless>count",
          "cvSeasonality" : null,
          "cvDetail" : null,
          "cvMethod" : null,
          "cvAdditionalInfo" : null,
          "cvFormat" : "Numeric",
          "cvShortName" : null
        } ],
        "NOAAKeywords" : [ "earth science>paleoclimate>tree-ring>width>latewood width" ]
      }, {
        "fileUrl" : "https://www.ncei.noaa.gov/pub/data/paleo/treering/chronologies/europe/aust007n-noaa.crn",
        "urlDescription" : "Chronology - NOAA Template File",
        "linkText" : "aust007n-noaa.crn",
        "variables" : [ {
          "cvDataType" : "TREE RING",
          "cvWhat" : "age variable>age",
          "cvMaterial" : null,
          "cvError" : null,
          "cvUnit" : "time unit>age unit>year Common Era",
          "cvSeasonality" : null,
          "cvDetail" : null,
          "cvMethod" : null,
          "cvAdditionalInfo" : null,
          "cvFormat" : "Numeric",
          "cvShortName" : null
        }, {
          "cvDataType" : "TREE RING",
          "cvWhat" : "sampling metadata>number of samples",
          "cvMaterial" : null,
          "cvError" : null,
          "cvUnit" : "dimensionless>count",
          "cvSeasonality" : null,
          "cvDetail" : null,
          "cvMethod" : null,
          "cvAdditionalInfo" : null,
          "cvFormat" : "Numeric",
          "cvShortName" : null
        }, {
          "cvDataType" : "TREE RING",
          "cvWhat" : "statistical variable>proxy composite>tree ring standardized growth index",
          "cvMaterial" : null,
          "cvError" : null,
          "cvUnit" : null,
          "cvSeasonality" : null,
          "cvDetail" : "composited",
          "cvMethod" : "computational method>tree ring chronology method>standard chronology method",
          "cvAdditionalInfo" : "reconstructed from minimum density",
          "cvFormat" : "Numeric",
          "cvShortName" : null
        } ],
        "NOAAKeywords" : [ "earth science>paleoclimate>tree-ring>density>minimum density" ]
      }, {
        "fileUrl" : "https://www.ncei.noaa.gov/pub/data/paleo/treering/chronologies/europe/aust007nr-noaa.crn",
        "urlDescription" : "Chronology - NOAA Template File",
        "linkText" : "aust007nr-noaa.crn",
        "variables" : [ {
          "cvDataType" : "TREE RING",
          "cvWhat" : "age variable>age",
          "cvMaterial" : null,
          "cvError" : null,
          "cvUnit" : "time unit>age unit>year Common Era",
          "cvSeasonality" : null,
          "cvDetail" : null,
          "cvMethod" : null,
          "cvAdditionalInfo" : null,
          "cvFormat" : "Numeric",
          "cvShortName" : null
        }, {
          "cvDataType" : "TREE RING",
          "cvWhat" : "statistical variable>proxy composite>tree ring standardized growth index",
          "cvMaterial" : null,
          "cvError" : null,
          "cvUnit" : null,
          "cvSeasonality" : null,
          "cvDetail" : "composited",
          "cvMethod" : "computational method>tree ring chronology method>residual chronology method",
          "cvAdditionalInfo" : "reconstructed from minimum density",
          "cvFormat" : "Numeric",
          "cvShortName" : null
        }, {
          "cvDataType" : "TREE RING",
          "cvWhat" : "sampling metadata>number of samples",
          "cvMaterial" : null,
          "cvError" : null,
          "cvUnit" : "dimensionless>count",
          "cvSeasonality" : null,
          "cvDetail" : null,
          "cvMethod" : null,
          "cvAdditionalInfo" : null,
          "cvFormat" : "Numeric",
          "cvShortName" : null
        } ],
        "NOAAKeywords" : [ "earth science>paleoclimate>tree-ring>density>minimum density" ]
      }, {
        "fileUrl" : "https://www.ncei.noaa.gov/pub/data/paleo/treering/chronologies/europe/aust007na-noaa.crn",
        "urlDescription" : "Chronology - NOAA Template File",
        "linkText" : "aust007na-noaa.crn",
        "variables" : [ {
          "cvDataType" : "TREE RING",
          "cvWhat" : "age variable>age",
          "cvMaterial" : null,
          "cvError" : null,
          "cvUnit" : "time unit>age unit>year Common Era",
          "cvSeasonality" : null,
          "cvDetail" : null,
          "cvMethod" : null,
          "cvAdditionalInfo" : null,
          "cvFormat" : "Numeric",
          "cvShortName" : null
        }, {
          "cvDataType" : "TREE RING",
          "cvWhat" : "statistical variable>proxy composite>tree ring standardized growth index",
          "cvMaterial" : null,
          "cvError" : null,
          "cvUnit" : null,
          "cvSeasonality" : null,
          "cvDetail" : "composited",
          "cvMethod" : "computational method>tree ring chronology method>ARSTAN chronology method",
          "cvAdditionalInfo" : "reconstructed from minimum density",
          "cvFormat" : "Numeric",
          "cvShortName" : null
        }, {
          "cvDataType" : "TREE RING",
          "cvWhat" : "sampling metadata>number of samples",
          "cvMaterial" : null,
          "cvError" : null,
          "cvUnit" : "dimensionless>count",
          "cvSeasonality" : null,
          "cvDetail" : null,
          "cvMethod" : null,
          "cvAdditionalInfo" : null,
          "cvFormat" : "Numeric",
          "cvShortName" : null
        } ],
        "NOAAKeywords" : [ "earth science>paleoclimate>tree-ring>density>minimum density" ]
      }, {
        "fileUrl" : "https://www.ncei.noaa.gov/pub/data/paleo/treering/chronologies/europe/aust007x-noaa.crn",
        "urlDescription" : "Chronology - NOAA Template File",
        "linkText" : "aust007x-noaa.crn",
        "variables" : [ {
          "cvDataType" : "TREE RING",
          "cvWhat" : "age variable>age",
          "cvMaterial" : null,
          "cvError" : null,
          "cvUnit" : "time unit>age unit>year Common Era",
          "cvSeasonality" : null,
          "cvDetail" : null,
          "cvMethod" : null,
          "cvAdditionalInfo" : null,
          "cvFormat" : "Numeric",
          "cvShortName" : null
        }, {
          "cvDataType" : "TREE RING",
          "cvWhat" : "sampling metadata>number of samples",
          "cvMaterial" : null,
          "cvError" : null,
          "cvUnit" : "dimensionless>count",
          "cvSeasonality" : null,
          "cvDetail" : null,
          "cvMethod" : null,
          "cvAdditionalInfo" : null,
          "cvFormat" : "Numeric",
          "cvShortName" : null
        }, {
          "cvDataType" : "TREE RING",
          "cvWhat" : "statistical variable>proxy composite>tree ring standardized growth index",
          "cvMaterial" : null,
          "cvError" : null,
          "cvUnit" : null,
          "cvSeasonality" : null,
          "cvDetail" : "composited",
          "cvMethod" : "computational method>tree ring chronology method>standard chronology method",
          "cvAdditionalInfo" : "reconstructed from maximum density",
          "cvFormat" : "Numeric",
          "cvShortName" : null
        } ],
        "NOAAKeywords" : [ "earth science>paleoclimate>tree-ring>density>maximum density" ]
      }, {
        "fileUrl" : "https://www.ncei.noaa.gov/pub/data/paleo/treering/chronologies/europe/aust007xr-noaa.crn",
        "urlDescription" : "Chronology - NOAA Template File",
        "linkText" : "aust007xr-noaa.crn",
        "variables" : [ {
          "cvDataType" : "TREE RING",
          "cvWhat" : "age variable>age",
          "cvMaterial" : null,
          "cvError" : null,
          "cvUnit" : "time unit>age unit>year Common Era",
          "cvSeasonality" : null,
          "cvDetail" : null,
          "cvMethod" : null,
          "cvAdditionalInfo" : null,
          "cvFormat" : "Numeric",
          "cvShortName" : null
        }, {
          "cvDataType" : "TREE RING",
          "cvWhat" : "statistical variable>proxy composite>tree ring standardized growth index",
          "cvMaterial" : null,
          "cvError" : null,
          "cvUnit" : null,
          "cvSeasonality" : null,
          "cvDetail" : "composited",
          "cvMethod" : "computational method>tree ring chronology method>residual chronology method",
          "cvAdditionalInfo" : "reconstructed from maximum density",
          "cvFormat" : "Numeric",
          "cvShortName" : null
        }, {
          "cvDataType" : "TREE RING",
          "cvWhat" : "sampling metadata>number of samples",
          "cvMaterial" : null,
          "cvError" : null,
          "cvUnit" : "dimensionless>count",
          "cvSeasonality" : null,
          "cvDetail" : null,
          "cvMethod" : null,
          "cvAdditionalInfo" : null,
          "cvFormat" : "Numeric",
          "cvShortName" : null
        } ],
        "NOAAKeywords" : [ "earth science>paleoclimate>tree-ring>density>maximum density" ]
      }, {
        "fileUrl" : "https://www.ncei.noaa.gov/pub/data/paleo/treering/chronologies/europe/aust007xa-noaa.crn",
        "urlDescription" : "Chronology - NOAA Template File",
        "linkText" : "aust007xa-noaa.crn",
        "variables" : [ {
          "cvDataType" : "TREE RING",
          "cvWhat" : "age variable>age",
          "cvMaterial" : null,
          "cvError" : null,
          "cvUnit" : "time unit>age unit>year Common Era",
          "cvSeasonality" : null,
          "cvDetail" : null,
          "cvMethod" : null,
          "cvAdditionalInfo" : null,
          "cvFormat" : "Numeric",
          "cvShortName" : null
        }, {
          "cvDataType" : "TREE RING",
          "cvWhat" : "statistical variable>proxy composite>tree ring standardized growth index",
          "cvMaterial" : null,
          "cvError" : null,
          "cvUnit" : null,
          "cvSeasonality" : null,
          "cvDetail" : "composited",
          "cvMethod" : "computational method>tree ring chronology method>ARSTAN chronology method",
          "cvAdditionalInfo" : "reconstructed from maximum density",
          "cvFormat" : "Numeric",
          "cvShortName" : null
        }, {
          "cvDataType" : "TREE RING",
          "cvWhat" : "sampling metadata>number of samples",
          "cvMaterial" : null,
          "cvError" : null,
          "cvUnit" : "dimensionless>count",
          "cvSeasonality" : null,
          "cvDetail" : null,
          "cvMethod" : null,
          "cvAdditionalInfo" : null,
          "cvFormat" : "Numeric",
          "cvShortName" : null
        } ],
        "NOAAKeywords" : [ "earth science>paleoclimate>tree-ring>density>maximum density" ]
      }, {
        "fileUrl" : "https://www.ncei.noaa.gov/pub/data/paleo/treering/measurements/europe/aust007.rwl",
        "urlDescription" : "Raw Measurements",
        "linkText" : "aust007.rwl",
        "variables" : [ {
          "cvDataType" : "TREE RING",
          "cvWhat" : "age variable>age",
          "cvMaterial" : null,
          "cvError" : null,
          "cvUnit" : "time unit>age unit>year Common Era",
          "cvSeasonality" : null,
          "cvDetail" : null,
          "cvMethod" : null,
          "cvAdditionalInfo" : null,
          "cvFormat" : "Numeric",
          "cvShortName" : null
        }, {
          "cvDataType" : "TREE RING",
          "cvWhat" : "physical property>width>total ring width",
          "cvMaterial" : null,
          "cvError" : null,
          "cvUnit" : "length unit>millimeter",
          "cvSeasonality" : null,
          "cvDetail" : null,
          "cvMethod" : null,
          "cvAdditionalInfo" : "units are 0.01 mm if end-of-series marker is 999 and 0.001 mm if end-of-series marker is -9999",
          "cvFormat" : "Numeric",
          "cvShortName" : null
        } ],
        "NOAAKeywords" : [ "earth science>paleoclimate>tree-ring>width>ring width" ]
      }, {
        "fileUrl" : "https://www.ncei.noaa.gov/pub/data/paleo/treering/measurements/europe/aust007e.rwl",
        "urlDescription" : "Raw Measurements",
        "linkText" : "aust007e.rwl",
        "variables" : [ {
          "cvDataType" : "TREE RING",
          "cvWhat" : "age variable>age",
          "cvMaterial" : null,
          "cvError" : null,
          "cvUnit" : "time unit>age unit>year Common Era",
          "cvSeasonality" : null,
          "cvDetail" : null,
          "cvMethod" : null,
          "cvAdditionalInfo" : null,
          "cvFormat" : "Numeric",
          "cvShortName" : null
        }, {
          "cvDataType" : "TREE RING",
          "cvWhat" : "physical property>width>earlywood width",
          "cvMaterial" : null,
          "cvError" : null,
          "cvUnit" : "length unit>millimeter",
          "cvSeasonality" : null,
          "cvDetail" : null,
          "cvMethod" : null,
          "cvAdditionalInfo" : "units are 0.01 mm if end-of-series marker is 999 and 0.001 mm if end-of-series marker is -9999",
          "cvFormat" : "Numeric",
          "cvShortName" : null
        } ],
        "NOAAKeywords" : [ "earth science>paleoclimate>tree-ring>width>earlywood width" ]
      }, {
        "fileUrl" : "https://www.ncei.noaa.gov/pub/data/paleo/treering/measurements/europe/aust007l.rwl",
        "urlDescription" : "Raw Measurements",
        "linkText" : "aust007l.rwl",
        "variables" : [ {
          "cvDataType" : "TREE RING",
          "cvWhat" : "age variable>age",
          "cvMaterial" : null,
          "cvError" : null,
          "cvUnit" : "time unit>age unit>year Common Era",
          "cvSeasonality" : null,
          "cvDetail" : null,
          "cvMethod" : null,
          "cvAdditionalInfo" : null,
          "cvFormat" : "Numeric",
          "cvShortName" : null
        }, {
          "cvDataType" : "TREE RING",
          "cvWhat" : "physical property>width>latewood width",
          "cvMaterial" : null,
          "cvError" : null,
          "cvUnit" : "length unit>millimeter",
          "cvSeasonality" : null,
          "cvDetail" : null,
          "cvMethod" : null,
          "cvAdditionalInfo" : "units are 0.01 mm if end-of-series marker is 999 and 0.001 mm if end-of-series marker is -9999",
          "cvFormat" : "Numeric",
          "cvShortName" : null
        } ],
        "NOAAKeywords" : [ "earth science>paleoclimate>tree-ring>width>latewood width" ]
      }, {
        "fileUrl" : "https://www.ncei.noaa.gov/pub/data/paleo/treering/measurements/europe/aust007n.rwl",
        "urlDescription" : "Raw Measurements",
        "linkText" : "aust007n.rwl",
        "variables" : [ {
          "cvDataType" : "TREE RING",
          "cvWhat" : "age variable>age",
          "cvMaterial" : null,
          "cvError" : null,
          "cvUnit" : "time unit>age unit>year Common Era",
          "cvSeasonality" : null,
          "cvDetail" : null,
          "cvMethod" : null,
          "cvAdditionalInfo" : null,
          "cvFormat" : "Numeric",
          "cvShortName" : null
        }, {
          "cvDataType" : "TREE RING",
          "cvWhat" : "physical property>density>minimum density",
          "cvMaterial" : null,
          "cvError" : null,
          "cvUnit" : "linear density unit>gram per decimeter",
          "cvSeasonality" : null,
          "cvDetail" : null,
          "cvMethod" : null,
          "cvAdditionalInfo" : null,
          "cvFormat" : "Numeric",
          "cvShortName" : null
        } ],
        "NOAAKeywords" : [ "earth science>paleoclimate>tree-ring>density>minimum density" ]
      }, {
        "fileUrl" : "https://www.ncei.noaa.gov/pub/data/paleo/treering/measurements/europe/aust007x.rwl",
        "urlDescription" : "Raw Measurements",
        "linkText" : "aust007x.rwl",
        "variables" : [ {
          "cvDataType" : "TREE RING",
          "cvWhat" : "age variable>age",
          "cvMaterial" : null,
          "cvError" : null,
          "cvUnit" : "time unit>age unit>year Common Era",
          "cvSeasonality" : null,
          "cvDetail" : null,
          "cvMethod" : null,
          "cvAdditionalInfo" : null,
          "cvFormat" : "Numeric",
          "cvShortName" : null
        }, {
          "cvDataType" : "TREE RING",
          "cvWhat" : "physical property>density>maximum density",
          "cvMaterial" : null,
          "cvError" : null,
          "cvUnit" : "linear density unit>gram per decimeter",
          "cvSeasonality" : null,
          "cvDetail" : null,
          "cvMethod" : null,
          "cvAdditionalInfo" : null,
          "cvFormat" : "Numeric",
          "cvShortName" : null
        } ],
        "NOAAKeywords" : [ "earth science>paleoclimate>tree-ring>density>maximum density" ]
      }, {
        "fileUrl" : "https://www.ncei.noaa.gov/pub/data/paleo/treering/measurements/europe/aust007n-noaa.rwl",
        "urlDescription" : "Raw Measurements - NOAA Template File",
        "linkText" : "aust007n-noaa.rwl",
        "variables" : [ {
          "cvDataType" : "TREE RING",
          "cvWhat" : "physical property>density>minimum density",
          "cvMaterial" : null,
          "cvError" : null,
          "cvUnit" : "linear density unit>gram per decimeter",
          "cvSeasonality" : null,
          "cvDetail" : null,
          "cvMethod" : null,
          "cvAdditionalInfo" : "Tree ID: 249003; ",
          "cvFormat" : "Numeric",
          "cvShortName" : "249003_raw"
        }, {
          "cvDataType" : "TREE RING",
          "cvWhat" : "physical property>density>minimum density",
          "cvMaterial" : null,
          "cvError" : null,
          "cvUnit" : "linear density unit>gram per decimeter",
          "cvSeasonality" : null,
          "cvDetail" : null,
          "cvMethod" : null,
          "cvAdditionalInfo" : "Tree ID: 249004; ",
          "cvFormat" : "Numeric",
          "cvShortName" : "249004_raw"
        }, {
          "cvDataType" : "TREE RING",
          "cvWhat" : "physical property>density>minimum density",
          "cvMaterial" : null,
          "cvError" : null,
          "cvUnit" : "linear density unit>gram per decimeter",
          "cvSeasonality" : null,
          "cvDetail" : null,
          "cvMethod" : null,
          "cvAdditionalInfo" : "Tree ID: 249005; ",
          "cvFormat" : "Numeric",
          "cvShortName" : "249005_raw"
        }, {
          "cvDataType" : "TREE RING",
          "cvWhat" : "physical property>density>minimum density",
          "cvMaterial" : null,
          "cvError" : null,
          "cvUnit" : "linear density unit>gram per decimeter",
          "cvSeasonality" : null,
          "cvDetail" : null,
          "cvMethod" : null,
          "cvAdditionalInfo" : "Tree ID: 250007; ",
          "cvFormat" : "Numeric",
          "cvShortName" : "250007_raw"
        }, {
          "cvDataType" : "TREE RING",
          "cvWhat" : "physical property>density>minimum density",
          "cvMaterial" : null,
          "cvError" : null,
          "cvUnit" : "linear density unit>gram per decimeter",
          "cvSeasonality" : null,
          "cvDetail" : null,
          "cvMethod" : null,
          "cvAdditionalInfo" : "Tree ID: 250012; ",
          "cvFormat" : "Numeric",
          "cvShortName" : "250012_raw"
        }, {
          "cvDataType" : "TREE RING",
          "cvWhat" : "physical property>density>minimum density",
          "cvMaterial" : null,
          "cvError" : null,
          "cvUnit" : "linear density unit>gram per decimeter",
          "cvSeasonality" : null,
          "cvDetail" : null,
          "cvMethod" : null,
          "cvAdditionalInfo" : "Tree ID: 250013; ",
          "cvFormat" : "Numeric",
          "cvShortName" : "250013_raw"
        }, {
          "cvDataType" : "TREE RING",
          "cvWhat" : "physical property>density>minimum density",
          "cvMaterial" : null,
          "cvError" : null,
          "cvUnit" : "linear density unit>gram per decimeter",
          "cvSeasonality" : null,
          "cvDetail" : null,
          "cvMethod" : null,
          "cvAdditionalInfo" : "Tree ID: 250015; ",
          "cvFormat" : "Numeric",
          "cvShortName" : "250015_raw"
        }, {
          "cvDataType" : "TREE RING",
          "cvWhat" : "physical property>density>minimum density",
          "cvMaterial" : null,
          "cvError" : null,
          "cvUnit" : "linear density unit>gram per decimeter",
          "cvSeasonality" : null,
          "cvDetail" : null,
          "cvMethod" : null,
          "cvAdditionalInfo" : "Tree ID: 250017; ",
          "cvFormat" : "Numeric",
          "cvShortName" : "250017_raw"
        }, {
          "cvDataType" : "TREE RING",
          "cvWhat" : "physical property>density>minimum density",
          "cvMaterial" : null,
          "cvError" : null,
          "cvUnit" : "linear density unit>gram per decimeter",
          "cvSeasonality" : null,
          "cvDetail" : null,
          "cvMethod" : null,
          "cvAdditionalInfo" : "Tree ID: 250019; ",
          "cvFormat" : "Numeric",
          "cvShortName" : "250019_raw"
        }, {
          "cvDataType" : "TREE RING",
          "cvWhat" : "physical property>density>minimum density",
          "cvMaterial" : null,
          "cvError" : null,
          "cvUnit" : "linear density unit>gram per decimeter",
          "cvSeasonality" : null,
          "cvDetail" : null,
          "cvMethod" : null,
          "cvAdditionalInfo" : "Tree ID: 250020; ",
          "cvFormat" : "Numeric",
          "cvShortName" : "250020_raw"
        }, {
          "cvDataType" : "TREE RING",
          "cvWhat" : "physical property>density>minimum density",
          "cvMaterial" : null,
          "cvError" : null,
          "cvUnit" : "linear density unit>gram per decimeter",
          "cvSeasonality" : null,
          "cvDetail" : null,
          "cvMethod" : null,
          "cvAdditionalInfo" : "Tree ID: 250021; ",
          "cvFormat" : "Numeric",
          "cvShortName" : "250021_raw"
        }, {
          "cvDataType" : "TREE RING",
          "cvWhat" : "age variable>age",
          "cvMaterial" : null,
          "cvError" : null,
          "cvUnit" : "time unit>age unit>year Common Era",
          "cvSeasonality" : null,
          "cvDetail" : null,
          "cvMethod" : null,
          "cvAdditionalInfo" : null,
          "cvFormat" : "Numeric",
          "cvShortName" : "age_CE"
        }, {
          "cvDataType" : "TREE RING",
          "cvWhat" : "physical property>density>minimum density",
          "cvMaterial" : null,
          "cvError" : null,
          "cvUnit" : "linear density unit>gram per decimeter",
          "cvSeasonality" : null,
          "cvDetail" : null,
          "cvMethod" : null,
          "cvAdditionalInfo" : "Tree ID: 249001; ",
          "cvFormat" : "Numeric",
          "cvShortName" : "249001_raw"
        }, {
          "cvDataType" : "TREE RING",
          "cvWhat" : "physical property>density>minimum density",
          "cvMaterial" : null,
          "cvError" : null,
          "cvUnit" : "linear density unit>gram per decimeter",
          "cvSeasonality" : null,
          "cvDetail" : null,
          "cvMethod" : null,
          "cvAdditionalInfo" : "Tree ID: 249002; ",
          "cvFormat" : "Numeric",
          "cvShortName" : "249002_raw"
        } ],
        "NOAAKeywords" : [ "earth science>paleoclimate>tree-ring>width>more info" ]
      }, {
        "fileUrl" : "https://www.ncei.noaa.gov/pub/data/paleo/treering/measurements/europe/aust007x-noaa.rwl",
        "urlDescription" : "Raw Measurements - NOAA Template File",
        "linkText" : "aust007x-noaa.rwl",
        "variables" : [ {
          "cvDataType" : "TREE RING",
          "cvWhat" : "age variable>age",
          "cvMaterial" : null,
          "cvError" : null,
          "cvUnit" : "time unit>age unit>year Common Era",
          "cvSeasonality" : null,
          "cvDetail" : null,
          "cvMethod" : null,
          "cvAdditionalInfo" : null,
          "cvFormat" : "Numeric",
          "cvShortName" : "age_CE"
        }, {
          "cvDataType" : "TREE RING",
          "cvWhat" : "physical property>density>maximum density",
          "cvMaterial" : null,
          "cvError" : null,
          "cvUnit" : "linear density unit>gram per decimeter",
          "cvSeasonality" : null,
          "cvDetail" : null,
          "cvMethod" : null,
          "cvAdditionalInfo" : "Tree ID: 249001; ",
          "cvFormat" : "Numeric",
          "cvShortName" : "249001_raw"
        }, {
          "cvDataType" : "TREE RING",
          "cvWhat" : "physical property>density>maximum density",
          "cvMaterial" : null,
          "cvError" : null,
          "cvUnit" : "linear density unit>gram per decimeter",
          "cvSeasonality" : null,
          "cvDetail" : null,
          "cvMethod" : null,
          "cvAdditionalInfo" : "Tree ID: 249002; ",
          "cvFormat" : "Numeric",
          "cvShortName" : "249002_raw"
        }, {
          "cvDataType" : "TREE RING",
          "cvWhat" : "physical property>density>maximum density",
          "cvMaterial" : null,
          "cvError" : null,
          "cvUnit" : "linear density unit>gram per decimeter",
          "cvSeasonality" : null,
          "cvDetail" : null,
          "cvMethod" : null,
          "cvAdditionalInfo" : "Tree ID: 249003; ",
          "cvFormat" : "Numeric",
          "cvShortName" : "249003_raw"
        }, {
          "cvDataType" : "TREE RING",
          "cvWhat" : "physical property>density>maximum density",
          "cvMaterial" : null,
          "cvError" : null,
          "cvUnit" : "linear density unit>gram per decimeter",
          "cvSeasonality" : null,
          "cvDetail" : null,
          "cvMethod" : null,
          "cvAdditionalInfo" : "Tree ID: 249004; ",
          "cvFormat" : "Numeric",
          "cvShortName" : "249004_raw"
        }, {
          "cvDataType" : "TREE RING",
          "cvWhat" : "physical property>density>maximum density",
          "cvMaterial" : null,
          "cvError" : null,
          "cvUnit" : "linear density unit>gram per decimeter",
          "cvSeasonality" : null,
          "cvDetail" : null,
          "cvMethod" : null,
          "cvAdditionalInfo" : "Tree ID: 249005; ",
          "cvFormat" : "Numeric",
          "cvShortName" : "249005_raw"
        }, {
          "cvDataType" : "TREE RING",
          "cvWhat" : "physical property>density>maximum density",
          "cvMaterial" : null,
          "cvError" : null,
          "cvUnit" : "linear density unit>gram per decimeter",
          "cvSeasonality" : null,
          "cvDetail" : null,
          "cvMethod" : null,
          "cvAdditionalInfo" : "Tree ID: 250007; ",
          "cvFormat" : "Numeric",
          "cvShortName" : "250007_raw"
        }, {
          "cvDataType" : "TREE RING",
          "cvWhat" : "physical property>density>maximum density",
          "cvMaterial" : null,
          "cvError" : null,
          "cvUnit" : "linear density unit>gram per decimeter",
          "cvSeasonality" : null,
          "cvDetail" : null,
          "cvMethod" : null,
          "cvAdditionalInfo" : "Tree ID: 250012; ",
          "cvFormat" : "Numeric",
          "cvShortName" : "250012_raw"
        }, {
          "cvDataType" : "TREE RING",
          "cvWhat" : "physical property>density>maximum density",
          "cvMaterial" : null,
          "cvError" : null,
          "cvUnit" : "linear density unit>gram per decimeter",
          "cvSeasonality" : null,
          "cvDetail" : null,
          "cvMethod" : null,
          "cvAdditionalInfo" : "Tree ID: 250013; ",
          "cvFormat" : "Numeric",
          "cvShortName" : "250013_raw"
        }, {
          "cvDataType" : "TREE RING",
          "cvWhat" : "physical property>density>maximum density",
          "cvMaterial" : null,
          "cvError" : null,
          "cvUnit" : "linear density unit>gram per decimeter",
          "cvSeasonality" : null,
          "cvDetail" : null,
          "cvMethod" : null,
          "cvAdditionalInfo" : "Tree ID: 250015; ",
          "cvFormat" : "Numeric",
          "cvShortName" : "250015_raw"
        }, {
          "cvDataType" : "TREE RING",
          "cvWhat" : "physical property>density>maximum density",
          "cvMaterial" : null,
          "cvError" : null,
          "cvUnit" : "linear density unit>gram per decimeter",
          "cvSeasonality" : null,
          "cvDetail" : null,
          "cvMethod" : null,
          "cvAdditionalInfo" : "Tree ID: 250017; ",
          "cvFormat" : "Numeric",
          "cvShortName" : "250017_raw"
        }, {
          "cvDataType" : "TREE RING",
          "cvWhat" : "physical property>density>maximum density",
          "cvMaterial" : null,
          "cvError" : null,
          "cvUnit" : "linear density unit>gram per decimeter",
          "cvSeasonality" : null,
          "cvDetail" : null,
          "cvMethod" : null,
          "cvAdditionalInfo" : "Tree ID: 250019; ",
          "cvFormat" : "Numeric",
          "cvShortName" : "250019_raw"
        }, {
          "cvDataType" : "TREE RING",
          "cvWhat" : "physical property>density>maximum density",
          "cvMaterial" : null,
          "cvError" : null,
          "cvUnit" : "linear density unit>gram per decimeter",
          "cvSeasonality" : null,
          "cvDetail" : null,
          "cvMethod" : null,
          "cvAdditionalInfo" : "Tree ID: 250020; ",
          "cvFormat" : "Numeric",
          "cvShortName" : "250020_raw"
        }, {
          "cvDataType" : "TREE RING",
          "cvWhat" : "physical property>density>maximum density",
          "cvMaterial" : null,
          "cvError" : null,
          "cvUnit" : "linear density unit>gram per decimeter",
          "cvSeasonality" : null,
          "cvDetail" : null,
          "cvMethod" : null,
          "cvAdditionalInfo" : "Tree ID: 250021; ",
          "cvFormat" : "Numeric",
          "cvShortName" : "250021_raw"
        } ],
        "NOAAKeywords" : [ "earth science>paleoclimate>tree-ring>width>more info" ]
      }, {
        "fileUrl" : "https://www.ncei.noaa.gov/pub/data/paleo/treering/measurements/europe/aust007e-noaa.rwl",
        "urlDescription" : "Raw Measurements - NOAA Template File",
        "linkText" : "aust007e-noaa.rwl",
        "variables" : [ {
          "cvDataType" : "TREE RING",
          "cvWhat" : "age variable>age",
          "cvMaterial" : null,
          "cvError" : null,
          "cvUnit" : "time unit>age unit>year Common Era",
          "cvSeasonality" : null,
          "cvDetail" : null,
          "cvMethod" : null,
          "cvAdditionalInfo" : null,
          "cvFormat" : "Numeric",
          "cvShortName" : "age_CE"
        }, {
          "cvDataType" : "TREE RING",
          "cvWhat" : "physical property>width>earlywood width",
          "cvMaterial" : null,
          "cvError" : null,
          "cvUnit" : "length unit>millimeter",
          "cvSeasonality" : null,
          "cvDetail" : null,
          "cvMethod" : null,
          "cvAdditionalInfo" : "Tree ID: 249001; units are 0.01 mm if end-of-series marker is 999 and 0.001 mm if end-of-series marker is -9999",
          "cvFormat" : "Numeric",
          "cvShortName" : "249001_raw"
        }, {
          "cvDataType" : "TREE RING",
          "cvWhat" : "physical property>width>earlywood width",
          "cvMaterial" : null,
          "cvError" : null,
          "cvUnit" : "length unit>millimeter",
          "cvSeasonality" : null,
          "cvDetail" : null,
          "cvMethod" : null,
          "cvAdditionalInfo" : "Tree ID: 249002; units are 0.01 mm if end-of-series marker is 999 and 0.001 mm if end-of-series marker is -9999",
          "cvFormat" : "Numeric",
          "cvShortName" : "249002_raw"
        }, {
          "cvDataType" : "TREE RING",
          "cvWhat" : "physical property>width>earlywood width",
          "cvMaterial" : null,
          "cvError" : null,
          "cvUnit" : "length unit>millimeter",
          "cvSeasonality" : null,
          "cvDetail" : null,
          "cvMethod" : null,
          "cvAdditionalInfo" : "Tree ID: 249003; units are 0.01 mm if end-of-series marker is 999 and 0.001 mm if end-of-series marker is -9999",
          "cvFormat" : "Numeric",
          "cvShortName" : "249003_raw"
        }, {
          "cvDataType" : "TREE RING",
          "cvWhat" : "physical property>width>earlywood width",
          "cvMaterial" : null,
          "cvError" : null,
          "cvUnit" : "length unit>millimeter",
          "cvSeasonality" : null,
          "cvDetail" : null,
          "cvMethod" : null,
          "cvAdditionalInfo" : "Tree ID: 249004; units are 0.01 mm if end-of-series marker is 999 and 0.001 mm if end-of-series marker is -9999",
          "cvFormat" : "Numeric",
          "cvShortName" : "249004_raw"
        }, {
          "cvDataType" : "TREE RING",
          "cvWhat" : "physical property>width>earlywood width",
          "cvMaterial" : null,
          "cvError" : null,
          "cvUnit" : "length unit>millimeter",
          "cvSeasonality" : null,
          "cvDetail" : null,
          "cvMethod" : null,
          "cvAdditionalInfo" : "Tree ID: 249005; units are 0.01 mm if end-of-series marker is 999 and 0.001 mm if end-of-series marker is -9999",
          "cvFormat" : "Numeric",
          "cvShortName" : "249005_raw"
        }, {
          "cvDataType" : "TREE RING",
          "cvWhat" : "physical property>width>earlywood width",
          "cvMaterial" : null,
          "cvError" : null,
          "cvUnit" : "length unit>millimeter",
          "cvSeasonality" : null,
          "cvDetail" : null,
          "cvMethod" : null,
          "cvAdditionalInfo" : "Tree ID: 250007; units are 0.01 mm if end-of-series marker is 999 and 0.001 mm if end-of-series marker is -9999",
          "cvFormat" : "Numeric",
          "cvShortName" : "250007_raw"
        }, {
          "cvDataType" : "TREE RING",
          "cvWhat" : "physical property>width>earlywood width",
          "cvMaterial" : null,
          "cvError" : null,
          "cvUnit" : "length unit>millimeter",
          "cvSeasonality" : null,
          "cvDetail" : null,
          "cvMethod" : null,
          "cvAdditionalInfo" : "Tree ID: 250012; units are 0.01 mm if end-of-series marker is 999 and 0.001 mm if end-of-series marker is -9999",
          "cvFormat" : "Numeric",
          "cvShortName" : "250012_raw"
        }, {
          "cvDataType" : "TREE RING",
          "cvWhat" : "physical property>width>earlywood width",
          "cvMaterial" : null,
          "cvError" : null,
          "cvUnit" : "length unit>millimeter",
          "cvSeasonality" : null,
          "cvDetail" : null,
          "cvMethod" : null,
          "cvAdditionalInfo" : "Tree ID: 250013; units are 0.01 mm if end-of-series marker is 999 and 0.001 mm if end-of-series marker is -9999",
          "cvFormat" : "Numeric",
          "cvShortName" : "250013_raw"
        }, {
          "cvDataType" : "TREE RING",
          "cvWhat" : "physical property>width>earlywood width",
          "cvMaterial" : null,
          "cvError" : null,
          "cvUnit" : "length unit>millimeter",
          "cvSeasonality" : null,
          "cvDetail" : null,
          "cvMethod" : null,
          "cvAdditionalInfo" : "Tree ID: 250015; units are 0.01 mm if end-of-series marker is 999 and 0.001 mm if end-of-series marker is -9999",
          "cvFormat" : "Numeric",
          "cvShortName" : "250015_raw"
        }, {
          "cvDataType" : "TREE RING",
          "cvWhat" : "physical property>width>earlywood width",
          "cvMaterial" : null,
          "cvError" : null,
          "cvUnit" : "length unit>millimeter",
          "cvSeasonality" : null,
          "cvDetail" : null,
          "cvMethod" : null,
          "cvAdditionalInfo" : "Tree ID: 250017; units are 0.01 mm if end-of-series marker is 999 and 0.001 mm if end-of-series marker is -9999",
          "cvFormat" : "Numeric",
          "cvShortName" : "250017_raw"
        }, {
          "cvDataType" : "TREE RING",
          "cvWhat" : "physical property>width>earlywood width",
          "cvMaterial" : null,
          "cvError" : null,
          "cvUnit" : "length unit>millimeter",
          "cvSeasonality" : null,
          "cvDetail" : null,
          "cvMethod" : null,
          "cvAdditionalInfo" : "Tree ID: 250019; units are 0.01 mm if end-of-series marker is 999 and 0.001 mm if end-of-series marker is -9999",
          "cvFormat" : "Numeric",
          "cvShortName" : "250019_raw"
        }, {
          "cvDataType" : "TREE RING",
          "cvWhat" : "physical property>width>earlywood width",
          "cvMaterial" : null,
          "cvError" : null,
          "cvUnit" : "length unit>millimeter",
          "cvSeasonality" : null,
          "cvDetail" : null,
          "cvMethod" : null,
          "cvAdditionalInfo" : "Tree ID: 250020; units are 0.01 mm if end-of-series marker is 999 and 0.001 mm if end-of-series marker is -9999",
          "cvFormat" : "Numeric",
          "cvShortName" : "250020_raw"
        }, {
          "cvDataType" : "TREE RING",
          "cvWhat" : "physical property>width>earlywood width",
          "cvMaterial" : null,
          "cvError" : null,
          "cvUnit" : "length unit>millimeter",
          "cvSeasonality" : null,
          "cvDetail" : null,
          "cvMethod" : null,
          "cvAdditionalInfo" : "Tree ID: 250021; units are 0.01 mm if end-of-series marker is 999 and 0.001 mm if end-of-series marker is -9999",
          "cvFormat" : "Numeric",
          "cvShortName" : "250021_raw"
        } ],
        "NOAAKeywords" : [ "earth science>paleoclimate>tree-ring>width>more info" ]
      }, {
        "fileUrl" : "https://www.ncei.noaa.gov/pub/data/paleo/treering/measurements/europe/aust007l-noaa.rwl",
        "urlDescription" : "Raw Measurements - NOAA Template File",
        "linkText" : "aust007l-noaa.rwl",
        "variables" : [ {
          "cvDataType" : "TREE RING",
          "cvWhat" : "physical property>width>latewood width",
          "cvMaterial" : null,
          "cvError" : null,
          "cvUnit" : "length unit>millimeter",
          "cvSeasonality" : null,
          "cvDetail" : null,
          "cvMethod" : null,
          "cvAdditionalInfo" : "Tree ID: 249003; units are 0.01 mm if end-of-series marker is 999 and 0.001 mm if end-of-series marker is -9999",
          "cvFormat" : "Numeric",
          "cvShortName" : "249003_raw"
        }, {
          "cvDataType" : "TREE RING",
          "cvWhat" : "age variable>age",
          "cvMaterial" : null,
          "cvError" : null,
          "cvUnit" : "time unit>age unit>year Common Era",
          "cvSeasonality" : null,
          "cvDetail" : null,
          "cvMethod" : null,
          "cvAdditionalInfo" : null,
          "cvFormat" : "Numeric",
          "cvShortName" : "age_CE"
        }, {
          "cvDataType" : "TREE RING",
          "cvWhat" : "physical property>width>latewood width",
          "cvMaterial" : null,
          "cvError" : null,
          "cvUnit" : "length unit>millimeter",
          "cvSeasonality" : null,
          "cvDetail" : null,
          "cvMethod" : null,
          "cvAdditionalInfo" : "Tree ID: 249001; units are 0.01 mm if end-of-series marker is 999 and 0.001 mm if end-of-series marker is -9999",
          "cvFormat" : "Numeric",
          "cvShortName" : "249001_raw"
        }, {
          "cvDataType" : "TREE RING",
          "cvWhat" : "physical property>width>latewood width",
          "cvMaterial" : null,
          "cvError" : null,
          "cvUnit" : "length unit>millimeter",
          "cvSeasonality" : null,
          "cvDetail" : null,
          "cvMethod" : null,
          "cvAdditionalInfo" : "Tree ID: 249002; units are 0.01 mm if end-of-series marker is 999 and 0.001 mm if end-of-series marker is -9999",
          "cvFormat" : "Numeric",
          "cvShortName" : "249002_raw"
        }, {
          "cvDataType" : "TREE RING",
          "cvWhat" : "physical property>width>latewood width",
          "cvMaterial" : null,
          "cvError" : null,
          "cvUnit" : "length unit>millimeter",
          "cvSeasonality" : null,
          "cvDetail" : null,
          "cvMethod" : null,
          "cvAdditionalInfo" : "Tree ID: 249004; units are 0.01 mm if end-of-series marker is 999 and 0.001 mm if end-of-series marker is -9999",
          "cvFormat" : "Numeric",
          "cvShortName" : "249004_raw"
        }, {
          "cvDataType" : "TREE RING",
          "cvWhat" : "physical property>width>latewood width",
          "cvMaterial" : null,
          "cvError" : null,
          "cvUnit" : "length unit>millimeter",
          "cvSeasonality" : null,
          "cvDetail" : null,
          "cvMethod" : null,
          "cvAdditionalInfo" : "Tree ID: 249005; units are 0.01 mm if end-of-series marker is 999 and 0.001 mm if end-of-series marker is -9999",
          "cvFormat" : "Numeric",
          "cvShortName" : "249005_raw"
        }, {
          "cvDataType" : "TREE RING",
          "cvWhat" : "physical property>width>latewood width",
          "cvMaterial" : null,
          "cvError" : null,
          "cvUnit" : "length unit>millimeter",
          "cvSeasonality" : null,
          "cvDetail" : null,
          "cvMethod" : null,
          "cvAdditionalInfo" : "Tree ID: 250007; units are 0.01 mm if end-of-series marker is 999 and 0.001 mm if end-of-series marker is -9999",
          "cvFormat" : "Numeric",
          "cvShortName" : "250007_raw"
        }, {
          "cvDataType" : "TREE RING",
          "cvWhat" : "physical property>width>latewood width",
          "cvMaterial" : null,
          "cvError" : null,
          "cvUnit" : "length unit>millimeter",
          "cvSeasonality" : null,
          "cvDetail" : null,
          "cvMethod" : null,
          "cvAdditionalInfo" : "Tree ID: 250012; units are 0.01 mm if end-of-series marker is 999 and 0.001 mm if end-of-series marker is -9999",
          "cvFormat" : "Numeric",
          "cvShortName" : "250012_raw"
        }, {
          "cvDataType" : "TREE RING",
          "cvWhat" : "physical property>width>latewood width",
          "cvMaterial" : null,
          "cvError" : null,
          "cvUnit" : "length unit>millimeter",
          "cvSeasonality" : null,
          "cvDetail" : null,
          "cvMethod" : null,
          "cvAdditionalInfo" : "Tree ID: 250013; units are 0.01 mm if end-of-series marker is 999 and 0.001 mm if end-of-series marker is -9999",
          "cvFormat" : "Numeric",
          "cvShortName" : "250013_raw"
        }, {
          "cvDataType" : "TREE RING",
          "cvWhat" : "physical property>width>latewood width",
          "cvMaterial" : null,
          "cvError" : null,
          "cvUnit" : "length unit>millimeter",
          "cvSeasonality" : null,
          "cvDetail" : null,
          "cvMethod" : null,
          "cvAdditionalInfo" : "Tree ID: 250015; units are 0.01 mm if end-of-series marker is 999 and 0.001 mm if end-of-series marker is -9999",
          "cvFormat" : "Numeric",
          "cvShortName" : "250015_raw"
        }, {
          "cvDataType" : "TREE RING",
          "cvWhat" : "physical property>width>latewood width",
          "cvMaterial" : null,
          "cvError" : null,
          "cvUnit" : "length unit>millimeter",
          "cvSeasonality" : null,
          "cvDetail" : null,
          "cvMethod" : null,
          "cvAdditionalInfo" : "Tree ID: 250017; units are 0.01 mm if end-of-series marker is 999 and 0.001 mm if end-of-series marker is -9999",
          "cvFormat" : "Numeric",
          "cvShortName" : "250017_raw"
        }, {
          "cvDataType" : "TREE RING",
          "cvWhat" : "physical property>width>latewood width",
          "cvMaterial" : null,
          "cvError" : null,
          "cvUnit" : "length unit>millimeter",
          "cvSeasonality" : null,
          "cvDetail" : null,
          "cvMethod" : null,
          "cvAdditionalInfo" : "Tree ID: 250019; units are 0.01 mm if end-of-series marker is 999 and 0.001 mm if end-of-series marker is -9999",
          "cvFormat" : "Numeric",
          "cvShortName" : "250019_raw"
        }, {
          "cvDataType" : "TREE RING",
          "cvWhat" : "physical property>width>latewood width",
          "cvMaterial" : null,
          "cvError" : null,
          "cvUnit" : "length unit>millimeter",
          "cvSeasonality" : null,
          "cvDetail" : null,
          "cvMethod" : null,
          "cvAdditionalInfo" : "Tree ID: 250020; units are 0.01 mm if end-of-series marker is 999 and 0.001 mm if end-of-series marker is -9999",
          "cvFormat" : "Numeric",
          "cvShortName" : "250020_raw"
        }, {
          "cvDataType" : "TREE RING",
          "cvWhat" : "physical property>width>latewood width",
          "cvMaterial" : null,
          "cvError" : null,
          "cvUnit" : "length unit>millimeter",
          "cvSeasonality" : null,
          "cvDetail" : null,
          "cvMethod" : null,
          "cvAdditionalInfo" : "Tree ID: 250021; units are 0.01 mm if end-of-series marker is 999 and 0.001 mm if end-of-series marker is -9999",
          "cvFormat" : "Numeric",
          "cvShortName" : "250021_raw"
        } ],
        "NOAAKeywords" : [ "earth science>paleoclimate>tree-ring>width>more info" ]
      }, {
        "fileUrl" : "https://www.ncei.noaa.gov/pub/data/paleo/treering/measurements/europe/aust007-noaa.rwl",
        "urlDescription" : "Raw Measurements - NOAA Template File",
        "linkText" : "aust007-noaa.rwl",
        "variables" : [ {
          "cvDataType" : "TREE RING",
          "cvWhat" : "age variable>age",
          "cvMaterial" : null,
          "cvError" : null,
          "cvUnit" : "time unit>age unit>year Common Era",
          "cvSeasonality" : null,
          "cvDetail" : null,
          "cvMethod" : null,
          "cvAdditionalInfo" : null,
          "cvFormat" : "Numeric",
          "cvShortName" : "age_CE"
        }, {
          "cvDataType" : "TREE RING",
          "cvWhat" : "physical property>width>total ring width",
          "cvMaterial" : null,
          "cvError" : null,
          "cvUnit" : "length unit>millimeter",
          "cvSeasonality" : null,
          "cvDetail" : null,
          "cvMethod" : null,
          "cvAdditionalInfo" : "Tree ID: 249001; units are 0.01 mm if end-of-series marker is 999 and 0.001 mm if end-of-series marker is -9999",
          "cvFormat" : "Numeric",
          "cvShortName" : "249001_raw"
        }, {
          "cvDataType" : "TREE RING",
          "cvWhat" : "physical property>width>total ring width",
          "cvMaterial" : null,
          "cvError" : null,
          "cvUnit" : "length unit>millimeter",
          "cvSeasonality" : null,
          "cvDetail" : null,
          "cvMethod" : null,
          "cvAdditionalInfo" : "Tree ID: 249002; units are 0.01 mm if end-of-series marker is 999 and 0.001 mm if end-of-series marker is -9999",
          "cvFormat" : "Numeric",
          "cvShortName" : "249002_raw"
        }, {
          "cvDataType" : "TREE RING",
          "cvWhat" : "physical property>width>total ring width",
          "cvMaterial" : null,
          "cvError" : null,
          "cvUnit" : "length unit>millimeter",
          "cvSeasonality" : null,
          "cvDetail" : null,
          "cvMethod" : null,
          "cvAdditionalInfo" : "Tree ID: 249003; units are 0.01 mm if end-of-series marker is 999 and 0.001 mm if end-of-series marker is -9999",
          "cvFormat" : "Numeric",
          "cvShortName" : "249003_raw"
        }, {
          "cvDataType" : "TREE RING",
          "cvWhat" : "physical property>width>total ring width",
          "cvMaterial" : null,
          "cvError" : null,
          "cvUnit" : "length unit>millimeter",
          "cvSeasonality" : null,
          "cvDetail" : null,
          "cvMethod" : null,
          "cvAdditionalInfo" : "Tree ID: 249004; units are 0.01 mm if end-of-series marker is 999 and 0.001 mm if end-of-series marker is -9999",
          "cvFormat" : "Numeric",
          "cvShortName" : "249004_raw"
        }, {
          "cvDataType" : "TREE RING",
          "cvWhat" : "physical property>width>total ring width",
          "cvMaterial" : null,
          "cvError" : null,
          "cvUnit" : "length unit>millimeter",
          "cvSeasonality" : null,
          "cvDetail" : null,
          "cvMethod" : null,
          "cvAdditionalInfo" : "Tree ID: 249005; units are 0.01 mm if end-of-series marker is 999 and 0.001 mm if end-of-series marker is -9999",
          "cvFormat" : "Numeric",
          "cvShortName" : "249005_raw"
        }, {
          "cvDataType" : "TREE RING",
          "cvWhat" : "physical property>width>total ring width",
          "cvMaterial" : null,
          "cvError" : null,
          "cvUnit" : "length unit>millimeter",
          "cvSeasonality" : null,
          "cvDetail" : null,
          "cvMethod" : null,
          "cvAdditionalInfo" : "Tree ID: 250007; units are 0.01 mm if end-of-series marker is 999 and 0.001 mm if end-of-series marker is -9999",
          "cvFormat" : "Numeric",
          "cvShortName" : "250007_raw"
        }, {
          "cvDataType" : "TREE RING",
          "cvWhat" : "physical property>width>total ring width",
          "cvMaterial" : null,
          "cvError" : null,
          "cvUnit" : "length unit>millimeter",
          "cvSeasonality" : null,
          "cvDetail" : null,
          "cvMethod" : null,
          "cvAdditionalInfo" : "Tree ID: 250012; units are 0.01 mm if end-of-series marker is 999 and 0.001 mm if end-of-series marker is -9999",
          "cvFormat" : "Numeric",
          "cvShortName" : "250012_raw"
        }, {
          "cvDataType" : "TREE RING",
          "cvWhat" : "physical property>width>total ring width",
          "cvMaterial" : null,
          "cvError" : null,
          "cvUnit" : "length unit>millimeter",
          "cvSeasonality" : null,
          "cvDetail" : null,
          "cvMethod" : null,
          "cvAdditionalInfo" : "Tree ID: 250013; units are 0.01 mm if end-of-series marker is 999 and 0.001 mm if end-of-series marker is -9999",
          "cvFormat" : "Numeric",
          "cvShortName" : "250013_raw"
        }, {
          "cvDataType" : "TREE RING",
          "cvWhat" : "physical property>width>total ring width",
          "cvMaterial" : null,
          "cvError" : null,
          "cvUnit" : "length unit>millimeter",
          "cvSeasonality" : null,
          "cvDetail" : null,
          "cvMethod" : null,
          "cvAdditionalInfo" : "Tree ID: 250015; units are 0.01 mm if end-of-series marker is 999 and 0.001 mm if end-of-series marker is -9999",
          "cvFormat" : "Numeric",
          "cvShortName" : "250015_raw"
        }, {
          "cvDataType" : "TREE RING",
          "cvWhat" : "physical property>width>total ring width",
          "cvMaterial" : null,
          "cvError" : null,
          "cvUnit" : "length unit>millimeter",
          "cvSeasonality" : null,
          "cvDetail" : null,
          "cvMethod" : null,
          "cvAdditionalInfo" : "Tree ID: 250017; units are 0.01 mm if end-of-series marker is 999 and 0.001 mm if end-of-series marker is -9999",
          "cvFormat" : "Numeric",
          "cvShortName" : "250017_raw"
        }, {
          "cvDataType" : "TREE RING",
          "cvWhat" : "physical property>width>total ring width",
          "cvMaterial" : null,
          "cvError" : null,
          "cvUnit" : "length unit>millimeter",
          "cvSeasonality" : null,
          "cvDetail" : null,
          "cvMethod" : null,
          "cvAdditionalInfo" : "Tree ID: 250019; units are 0.01 mm if end-of-series marker is 999 and 0.001 mm if end-of-series marker is -9999",
          "cvFormat" : "Numeric",
          "cvShortName" : "250019_raw"
        }, {
          "cvDataType" : "TREE RING",
          "cvWhat" : "physical property>width>total ring width",
          "cvMaterial" : null,
          "cvError" : null,
          "cvUnit" : "length unit>millimeter",
          "cvSeasonality" : null,
          "cvDetail" : null,
          "cvMethod" : null,
          "cvAdditionalInfo" : "Tree ID: 250020; units are 0.01 mm if end-of-series marker is 999 and 0.001 mm if end-of-series marker is -9999",
          "cvFormat" : "Numeric",
          "cvShortName" : "250020_raw"
        }, {
          "cvDataType" : "TREE RING",
          "cvWhat" : "physical property>width>total ring width",
          "cvMaterial" : null,
          "cvError" : null,
          "cvUnit" : "length unit>millimeter",
          "cvSeasonality" : null,
          "cvDetail" : null,
          "cvMethod" : null,
          "cvAdditionalInfo" : "Tree ID: 250021; units are 0.01 mm if end-of-series marker is 999 and 0.001 mm if end-of-series marker is -9999",
          "cvFormat" : "Numeric",
          "cvShortName" : "250021_raw"
        } ],
        "NOAAKeywords" : [ "earth science>paleoclimate>tree-ring>width>more info" ]
      } ]
    } ]
  } ],
  "reference" : {
    "pastThesaurusSkos" : "https://www.ncei.noaa.gov/access/paleo-search/skos/past-thesaurus.rdf",
    "pastThesaurusExplorer" : "https://www.ncei.noaa.gov/access/paleo-search/cvterms",
    "gcmdKeywordThesaurus" : "https://earthdata.nasa.gov/earth-observation-data/find-data/idn/gcmd-keywords"
  }
}